chromeprinter/__init__.py
chromeprinter-0.0.2.dist-info/METADATA
chromeprinter-0.0.2.dist-info/WHEEL
chromeprinter-0.0.2.dist-info/top_level.txt
chromeprinter-0.0.2.dist-info/RECORD
