Metadata-Version: 2.1
Name: chromeprinter
Version: 0.0.2
Summary: Print chrome page with chromedriver
Home-page: UNKNOWN
Author: OLixao
Author-email: contact@olixao.ml
License: UNKNOWN
Platform: UNKNOWN
Requires-Dist: selenium
